aiosubgram/__init__.py
aiosubgram/base.py
aiosubgram/client.py
aiosubgram/exceptions.py
aiosubgram/methods/__init__.py
aiosubgram/methods/advertiser.py
aiosubgram/methods/base.py
aiosubgram/methods/general.py
aiosubgram/methods/publisher.py
aiosubgram/types/__init__.py
aiosubgram/types/advertiser.py
aiosubgram/types/base.py
aiosubgram/types/general.py
aiosubgram/types/publisher.py
aiosubgram/utils/__init__.py
aiosubgram/utils/keyboard.py
aiosubgram/utils/middleware.py
aiosubgram-1.0.1.dist-info/LICENSE
aiosubgram-1.0.1.dist-info/METADATA
aiosubgram-1.0.1.dist-info/WHEEL
aiosubgram-1.0.1.dist-info/top_level.txt
aiosubgram-1.0.1.dist-info/RECORD
