Metadata-Version: 2.1
Name: aiosubgram
Version: 1.0.1
Summary: Asynchronous library for working with subgram.org
Home-page: https://github.com/salatcs/aiosubgram
Author: salatcs
Author-email: salatcs03@gmail.com
Classifier: Programming Language :: Python :: 3
Classifier: License :: OSI Approved :: MIT License
Classifier: Operating System :: OS Independent
Requires-Python: >=3.9
License-File: LICENSE
Requires-Dist: aiohttp==3.13.2
Requires-Dist: pydantic>=2.0
Requires-Dist: aiogram>=3.22.0
